README.md
setup.py
manas/__init__.py
manas.egg-info/PKG-INFO
manas.egg-info/SOURCES.txt
manas.egg-info/dependency_links.txt
manas.egg-info/top_level.txt