Metadata-Version: 2.1
Name: manas
Version: 0.0.0
Summary: A Framework for Conceptual Networks
Author: Bowen Xu
Author-email: bowen.xu@temple.edu
License: MIT
Keywords: manas,conceptual network
Classifier: Development Status :: 2 - Pre-Alpha
Classifier: Intended Audience :: Developers
Classifier: License :: OSI Approved :: MIT License
Classifier: Natural Language :: English
Classifier: Natural Language :: Chinese (Simplified)
Classifier: Programming Language :: Python :: 3.7
Classifier: Programming Language :: Python :: 3.8
Classifier: Programming Language :: Python :: 3.9
Classifier: Programming Language :: Python :: 3.10
Classifier: Programming Language :: Python :: 3.10
Requires-Python: >=3.7.0
